[{"__type__":"cc.SpriteFrame","content":{"name":"harmful_mouse_1_death","texture":"59+9imivFHWr9ZSOwJZdq1","rect":[0,84,120,87],"offset":[0,0],"originalSize":[120,87],"capInsets":[0,0,0,0]}},{"__type__":"cc.SpriteAtlas","_name":"animal_death.plist","_spriteFrames":{"harmful_mouse_0_death":{"__uuid__":"ffqzAMIqRPx5CHSijgbRy4"},"harmful_mouse_1_death":{"__uuid__":"0eD1xWPQ9BJJ/lq5VhfgMV"},"kind_mouse_0_death":{"__uuid__":"897BFwS21BZ7KxETun0itf"},"kind_mouse_1_death":{"__uuid__":"c0bAoUJI9KIoVIn8cPnDyK"},"rabbit_0_death":{"__uuid__":"b6IHecUB1I/7nBcDz3EfgS"}}},{"__type__":"cc.SpriteFrame","content":{"name":"kind_mouse_0_death","texture":"59+9imivFHWr9ZSOwJZdq1","rect":[0,171,117,70],"offset":[0,0],"originalSize":[117,70],"capInsets":[0,0,0,0]}},{"__type__":"cc.SpriteFrame","content":{"name":"rabbit_0_death","texture":"59+9imivFHWr9ZSOwJZdq1","rect":[0,306,117,69],"offset":[0,0],"originalSize":[117,69],"capInsets":[0,0,0,0]}},{"__type__":"cc.SpriteFrame","content":{"name":"kind_mouse_1_death","texture":"59+9imivFHWr9ZSOwJZdq1","rect":[0,241,83,65],"offset":[0,0],"originalSize":[83,65],"capInsets":[0,0,0,0]}},{"__type__":"cc.SpriteFrame","content":{"name":"harmful_mouse_0_death","texture":"59+9imivFHWr9ZSOwJZdq1","rect":[0,0,122,84],"offset":[0,0],"originalSize":[122,84],"capInsets":[0,0,0,0]}}]