[{"__type__":"cc.SpriteFrame","content":{"name":"Common (160)","texture":"73No2pnf9Iz7LzhRncubTB","rect":[634,812,52,68],"offset":[-1,2],"originalSize":[60,76],"capInsets":[0,0,0,0]}},{"__type__":"cc.SpriteFrame","content":{"name":"Common (128)","texture":"73No2pnf9Iz7LzhRncubTB","rect":[446,2,456,36],"offset":[0,0],"originalSize":[456,36],"capInsets":[0,0,0,0]}},{"__type__":"cc.SpriteFrame","content":{"name":"Common (113)","texture":"73No2pnf9Iz7LzhRncubTB","rect":[230,753,148,52],"offset":[0,0],"originalSize":[148,52],"capInsets":[0,0,0,0]}},{"__type__":"cc.SpriteFrame","content":{"name":"Common (62)","texture":"73No2pnf9Iz7LzhRncubTB","rect":[662,464,106,60],"offset":[0,0],"originalSize":[106,60],"capInsets":[0,0,0,0]}},{"__type__":"cc.SpriteFrame","content":{"name":"Common (86)","texture":"73No2pnf9Iz7LzhRncubTB","rect":[992,786,24,22],"offset":[0,0],"originalSize":[24,22],"capInsets":[0,0,0,0]}},{"__type__":"cc.SpriteFrame","content":{"name":"Common (146)","texture":"73No2pnf9Iz7LzhRncubTB","rect":[938,708,40,34],"offset":[0,0],"originalSize":[40,34],"capInsets":[0,0,0,0]}},{"__type__":"cc.SpriteFrame","content":{"name":"Common (39)","texture":"73No2pnf9Iz7LzhRncubTB","rect":[976,750,36,34],"offset":[0,0],"originalSize":[36,34],"capInsets":[8,8,8,8]}},{"__type__":"cc.SpriteFrame","content":{"name":"Common (15)","texture":"73No2pnf9Iz7LzhRncubTB","rect":[2,170,190,186],"offset":[0,0],"originalSize":[190,186],"capInsets":[0,0,0,0]}},{"__type__":"cc.SpriteFrame","content":{"name":"Common (52)","texture":"73No2pnf9Iz7LzhRncubTB","rect":[2,807,136,86],"offset":[0,0],"originalSize":[136,86],"capInsets":[0,0,0,0]}},{"__type__":"cc.SpriteFrame","content":{"name":"Common (97)","texture":"73No2pnf9Iz7LzhRncubTB","rect":[770,516,84,34],"offset":[0,0],"originalSize":[84,34],"capInsets":[7,7,7,7]}},{"__type__":"cc.SpriteFrame","content":{"name":"Common (16)","texture":"73No2pnf9Iz7LzhRncubTB","rect":[490,672,114,70],"offset":[0,0],"originalSize":[114,70],"capInsets":[0,0,0,0]}},{"__type__":"cc.SpriteFrame","content":{"name":"Common (137)","texture":"73No2pnf9Iz7LzhRncubTB","rect":[392,402,133,74],"offset":[0,0],"originalSize":[133,74],"capInsets":[34,33,40,33]}},{"__type__":"cc.SpriteFrame","content":{"name":"Common (115)","texture":"73No2pnf9Iz7LzhRncubTB","rect":[838,342,24,24],"offset":[0,0],"originalSize":[24,24],"capInsets":[0,0,0,0]}},{"__type__":"cc.SpriteFrame","content":{"name":"Common (63)","texture":"73No2pnf9Iz7LzhRncubTB","rect":[844,746,34,40],"offset":[0,-1],"originalSize":[58,58],"capInsets":[0,0,0,0]}},{"__type__":"cc.SpriteFrame","content":{"name":"Common (19)","texture":"73No2pnf9Iz7LzhRncubTB","rect":[744,796,30,40],"offset":[0,0],"originalSize":[30,40],"capInsets":[6,6,6,6]}},{"__type__":"cc.SpriteFrame","content":{"name":"Common (96)","texture":"73No2pnf9Iz7LzhRncubTB","rect":[355,535,22,22],"offset":[0,0],"originalSize":[22,22],"capInsets":[0,0,0,0]}},{"__type__":"cc.SpriteFrame","content":{"name":"Common (94)","texture":"73No2pnf9Iz7LzhRncubTB","rect":[164,386,226,71],"offset":[0,0],"originalSize":[226,71],"capInsets":[0,0,0,0]}},{"__type__":"cc.SpriteFrame","content":{"name":"Common (142)","texture":"73No2pnf9Iz7LzhRncubTB","rect":[876,856,30,30],"offset":[0,0],"originalSize":[30,30],"capInsets":[0,0,0,0]}},{"__type__":"cc.SpriteFrame","content":{"name":"Common (129)","texture":"73No2pnf9Iz7LzhRncubTB","rect":[664,698,52,50],"offset":[0,0],"originalSize":[52,50],"capInsets":[0,0,0,0]}},{"__type__":"cc.SpriteFrame","content":{"name":"Common (65)","texture":"73No2pnf9Iz7LzhRncubTB","rect":[536,70,186,63],"offset":[0,0],"originalSize":[186,63],"capInsets":[0,0,0,0]}},{"__type__":"cc.SpriteFrame","content":{"name":"Common (81)","texture":"73No2pnf9Iz7LzhRncubTB","rect":[500,812,66,64],"offset":[0,-4],"originalSize":[84,84],"capInsets":[0,0,0,0]}},{"__type__":"cc.SpriteFrame","content":{"name":"Common (70)","texture":"73No2pnf9Iz7LzhRncubTB","rect":[912,742,24,30],"offset":[0,0],"originalSize":[24,30],"capInsets":[0,0,0,0]}},{"__type__":"cc.SpriteFrame","content":{"name":"Common (135)","texture":"73No2pnf9Iz7LzhRncubTB","rect":[390,478,132,62],"offset":[0,0],"originalSize":[132,62],"capInsets":[0,0,0,0]}},{"__type__":"cc.SpriteFrame","content":{"name":"Common (22)","texture":"73No2pnf9Iz7LzhRncubTB","rect":[758,552,64,62],"offset":[0,0],"originalSize":[64,62],"capInsets":[0,0,0,0]}},{"__type__":"cc.SpriteFrame","content":{"name":"Common (138)","texture":"73No2pnf9Iz7LzhRncubTB","rect":[970,856,18,18],"offset":[0,0],"originalSize":[18,18],"capInsets":[0,0,0,0]}},{"__type__":"cc.SpriteFrame","content":{"name":"Common (79)","texture":"73No2pnf9Iz7LzhRncubTB","rect":[654,574,60,72],"offset":[-1,-3],"originalSize":[84,84],"capInsets":[0,0,0,0]}},{"__type__":"cc.SpriteFrame","content":{"name":"Common (105)","texture":"73No2pnf9Iz7LzhRncubTB","rect":[250,699,138,52],"offset":[0,0],"originalSize":[138,52],"capInsets":[0,0,0,0]}},{"__type__":"cc.SpriteFrame","content":{"name":"Common (114)","texture":"73No2pnf9Iz7LzhRncubTB","rect":[990,852,18,18],"offset":[0,1],"originalSize":[24,24],"capInsets":[0,0,0,0]}},{"__type__":"cc.SpriteFrame","content":{"name":"Common (23)","texture":"73No2pnf9Iz7LzhRncubTB","rect":[864,356,80,76],"offset":[0,0],"originalSize":[80,76],"capInsets":[0,0,0,0]}},{"__type__":"cc.SpriteFrame","content":{"name":"Common (109)","texture":"73No2pnf9Iz7LzhRncubTB","rect":[688,810,54,58],"offset":[0,-2],"originalSize":[64,70],"capInsets":[0,0,0,0]}},{"__type__":"cc.SpriteFrame","content":{"name":"Common (73)","texture":"73No2pnf9Iz7LzhRncubTB","rect":[446,40,406,28],"offset":[0,0],"originalSize":[406,28],"capInsets":[0,0,0,0]}},{"__type__":"cc.SpriteFrame","content":{"name":"Common (72)","texture":"73No2pnf9Iz7LzhRncubTB","rect":[946,356,72,56],"offset":[0,0],"originalSize":[72,56],"capInsets":[0,0,0,0]}},{"__type__":"cc.SpriteFrame","content":{"name":"Common (29)","texture":"73No2pnf9Iz7LzhRncubTB","rect":[916,826,28,28],"offset":[0,0],"originalSize":[28,28],"capInsets":[0,0,0,0]}},{"__type__":"cc.SpriteFrame","content":{"name":"Common (144)","texture":"73No2pnf9Iz7LzhRncubTB","rect":[712,270,152,70],"offset":[0,0],"originalSize":[152,70],"capInsets":[0,0,0,0]}},{"__type__":"cc.SpriteFrame","content":{"name":"Common (101)","texture":"73No2pnf9Iz7LzhRncubTB","rect":[978,822,28,28],"offset":[0,0],"originalSize":[28,28],"capInsets":[0,0,0,0]}},{"__type__":"cc.SpriteFrame","content":{"name":"Common (85)","texture":"73No2pnf9Iz7LzhRncubTB","rect":[866,332,150,22],"offset":[0,0],"originalSize":[150,22],"capInsets":[0,0,0,0]}},{"__type__":"cc.SpriteFrame","content":{"name":"Common (6)","texture":"73No2pnf9Iz7LzhRncubTB","rect":[356,459,32,40],"offset":[0,0],"originalSize":[40,40],"capInsets":[0,0,0,0]}},{"__type__":"cc.SpriteFrame","content":{"name":"Common (132)","texture":"73No2pnf9Iz7LzhRncubTB","rect":[724,188,158,8],"offset":[0,0],"originalSize":[158,8],"capInsets":[0,0,0,0]}},{"__type__":"cc.SpriteFrame","content":{"name":"Common (123)","texture":"73No2pnf9Iz7LzhRncubTB","rect":[938,744,36,36],"offset":[0,0],"originalSize":[36,36],"capInsets":[0,0,0,0]}},{"__type__":"cc.SpriteFrame","content":{"name":"Common (153)","texture":"73No2pnf9Iz7LzhRncubTB","rect":[728,744,30,50],"offset":[0,0],"originalSize":[30,50],"capInsets":[12,15,12,12]}},{"__type__":"cc.SpriteFrame","content":{"name":"Common (1)","texture":"73No2pnf9Iz7LzhRncubTB","rect":[390,660,98,78],"offset":[0,0],"originalSize":[98,78],"capInsets":[0,0,0,0]}},{"__type__":"cc.SpriteFrame","content":{"name":"Common (116)","texture":"73No2pnf9Iz7LzhRncubTB","rect":[904,118,114,78],"offset":[0,0],"originalSize":[114,78],"capInsets":[0,0,0,0]}},{"__type__":"cc.SpriteFrame","content":{"name":"Common (8)","texture":"73No2pnf9Iz7LzhRncubTB","rect":[380,542,120,100],"offset":[0,-9],"originalSize":[140,140],"capInsets":[0,0,0,0]}},{"__type__":"cc.SpriteFrame","content":{"name":"Common (151)","texture":"73No2pnf9Iz7LzhRncubTB","rect":[953,502,60,60],"offset":[0,0],"originalSize":[60,60],"capInsets":[0,0,0,0]}},{"__type__":"cc.SpriteFrame","content":{"name":"Common (104)","texture":"73No2pnf9Iz7LzhRncubTB","rect":[892,660,44,42],"offset":[0,0],"originalSize":[44,42],"capInsets":[0,0,0,0]}},{"__type__":"cc.SpriteFrame","content":{"name":"Common (76)","texture":"73No2pnf9Iz7LzhRncubTB","rect":[724,120,176,66],"offset":[0,0],"originalSize":[176,66],"capInsets":[0,0,0,0]}},{"__type__":"cc.SpriteFrame","content":{"name":"Common (35)","texture":"73No2pnf9Iz7LzhRncubTB","rect":[990,674,28,34],"offset":[0,0],"originalSize":[34,34],"capInsets":[0,0,0,0]}},{"__type__":"cc.SpriteFrame","content":{"name":"Common (3)","texture":"73No2pnf9Iz7LzhRncubTB","rect":[664,648,48,48],"offset":[0,0],"originalSize":[48,48],"capInsets":[0,0,0,0]}},{"__type__":"cc.SpriteFrame","content":{"name":"Common (10)","texture":"73No2pnf9Iz7LzhRncubTB","rect":[502,548,96,122],"offset":[2,-1],"originalSize":[146,146],"capInsets":[0,0,0,0]}},{"__type__":"cc.SpriteFrame","content":{"name":"Common (53)","texture":"73No2pnf9Iz7LzhRncubTB","rect":[2,68,344,100],"offset":[0,0],"originalSize":[344,100],"capInsets":[0,0,0,0]}},{"__type__":"cc.SpriteFrame","content":{"name":"Common (102)","texture":"73No2pnf9Iz7LzhRncubTB","rect":[816,708,26,40],"offset":[0,0],"originalSize":[26,40],"capInsets":[9,17,9,17]}},{"__type__":"cc.SpriteFrame","content":{"name":"Common (60)","texture":"73No2pnf9Iz7LzhRncubTB","rect":[738,870,20,22],"offset":[0,0],"originalSize":[20,22],"capInsets":[0,0,0,0]}},{"__type__":"cc.SpriteFrame","content":{"name":"Common (17)","texture":"73No2pnf9Iz7LzhRncubTB","rect":[194,272,210,80],"offset":[0,0],"originalSize":[210,80],"capInsets":[0,0,0,0]}},{"__type__":"cc.SpriteFrame","content":{"name":"Common (14)","texture":"73No2pnf9Iz7LzhRncubTB","rect":[946,824,30,30],"offset":[0,0],"originalSize":[30,30],"capInsets":[12,12,12,12]}},{"__type__":"cc.SpriteFrame","content":{"name":"Common (126)","texture":"73No2pnf9Iz7LzhRncubTB","rect":[536,262,174,62],"offset":[0,0],"originalSize":[174,62],"capInsets":[0,0,0,0]}},{"__type__":"cc.SpriteFrame","content":{"name":"Common (26)","texture":"73No2pnf9Iz7LzhRncubTB","rect":[536,344,154,24],"offset":[0,0],"originalSize":[154,24],"capInsets":[0,0,0,0]}},{"__type__":"cc.SpriteFrame","content":{"name":"Common (108)","texture":"73No2pnf9Iz7LzhRncubTB","rect":[812,802,30,26],"offset":[0,0],"originalSize":[30,26],"capInsets":[0,0,0,0]}},{"__type__":"cc.SpriteFrame","content":{"name":"Common (154)","texture":"73No2pnf9Iz7LzhRncubTB","rect":[890,40,12,12],"offset":[0,0],"originalSize":[12,12],"capInsets":[5,5,5,5]}},{"__type__":"cc.SpriteFrame","content":{"name":"Common (68)","texture":"73No2pnf9Iz7LzhRncubTB","rect":[348,150,20,18],"offset":[0,0],"originalSize":[22,22],"capInsets":[0,0,0,0]}},{"__type__":"cc.SpriteFrame","content":{"name":"Common (38)","texture":"73No2pnf9Iz7LzhRncubTB","rect":[844,704,46,40],"offset":[0,0],"originalSize":[46,40],"capInsets":[0,0,0,0]}},{"__type__":"cc.SpriteFrame","content":{"name":"Common (34)","texture":"73No2pnf9Iz7LzhRncubTB","rect":[908,856,28,34],"offset":[0,0],"originalSize":[28,34],"capInsets":[0,0,0,0]}},{"__type__":"cc.SpriteFrame","content":{"name":"Common (18)","texture":"73No2pnf9Iz7LzhRncubTB","rect":[776,828,30,40],"offset":[0,0],"originalSize":[30,40],"capInsets":[6,6,6,6]}},{"__type__":"cc.SpriteFrame","content":{"name":"Common (7)","texture":"73No2pnf9Iz7LzhRncubTB","rect":[406,240,128,108],"offset":[1,1],"originalSize":[140,140],"capInsets":[0,0,0,0]}},{"__type__":"cc.SpriteFrame","content":{"name":"Common (71)","texture":"73No2pnf9Iz7LzhRncubTB","rect":[938,856,30,32],"offset":[0,0],"originalSize":[30,32],"capInsets":[0,0,0,0]}},{"__type__":"cc.SpriteFrame","content":{"name":"Common (84)","texture":"73No2pnf9Iz7LzhRncubTB","rect":[416,350,116,50],"offset":[0,0],"originalSize":[116,50],"capInsets":[12,15,12,12]}},{"__type__":"cc.SpriteFrame","content":{"name":"Common (118)","texture":"73No2pnf9Iz7LzhRncubTB","rect":[527,472,132,24],"offset":[0,0],"originalSize":[132,24],"capInsets":[0,0,0,0]}},{"__type__":"cc.SpriteFrame","content":{"name":"Common (110)","texture":"73No2pnf9Iz7LzhRncubTB","rect":[2,358,160,144],"offset":[0,0],"originalSize":[160,144],"capInsets":[0,0,0,0]}},{"__type__":"cc.SpriteFrame","content":{"name":"Common (43)","texture":"73No2pnf9Iz7LzhRncubTB","rect":[884,542,58,56],"offset":[0,0],"originalSize":[58,56],"capInsets":[0,0,0,0]}},{"__type__":"cc.SpriteFrame","content":{"name":"Common (66)","texture":"73No2pnf9Iz7LzhRncubTB","rect":[380,644,120,14],"offset":[0,0],"originalSize":[120,14],"capInsets":[0,0,0,0]}},{"__type__":"cc.SpriteFrame","content":{"name":"Common (120)","texture":"73No2pnf9Iz7LzhRncubTB","rect":[787,442,78,72],"offset":[1,-1],"originalSize":[90,90],"capInsets":[0,0,0,0]}},{"__type__":"cc.SpriteFrame","content":{"name":"Common (98)","texture":"73No2pnf9Iz7LzhRncubTB","rect":[867,506,84,34],"offset":[0,0],"originalSize":[84,34],"capInsets":[0,0,0,0]}},{"__type__":"cc.SpriteFrame","content":{"name":"Common (158)","texture":"73No2pnf9Iz7LzhRncubTB","rect":[524,498,136,48],"offset":[0,0],"originalSize":[136,48],"capInsets":[11,11,11,11]}},{"__type__":"cc.SpriteFrame","content":{"name":"Common (83)","texture":"73No2pnf9Iz7LzhRncubTB","rect":[494,744,78,66],"offset":[1,-2],"originalSize":[84,84],"capInsets":[0,0,0,0]}},{"__type__":"cc.SpriteFrame","content":{"name":"Common (157)","texture":"73No2pnf9Iz7LzhRncubTB","rect":[688,870,24,22],"offset":[0,0],"originalSize":[24,22],"capInsets":[0,0,0,0]}},{"__type__":"cc.SpriteFrame","content":{"name":"Common (77)","texture":"73No2pnf9Iz7LzhRncubTB","rect":[606,752,64,58],"offset":[0,-2],"originalSize":[64,64],"capInsets":[0,0,0,0]}},{"__type__":"cc.SpriteFrame","content":{"name":"Common (136)","texture":"73No2pnf9Iz7LzhRncubTB","rect":[424,746,68,68],"offset":[0,0],"originalSize":[68,68],"capInsets":[0,0,0,0]}},{"__type__":"cc.SpriteFrame","content":{"name":"Common (64)","texture":"73No2pnf9Iz7LzhRncubTB","rect":[536,135,186,63],"offset":[0,0],"originalSize":[186,63],"capInsets":[0,0,0,0]}},{"__type__":"cc.SpriteFrame","content":{"name":"Common (30)","texture":"73No2pnf9Iz7LzhRncubTB","rect":[808,830,34,34],"offset":[0,0],"originalSize":[34,34],"capInsets":[0,0,0,0]}},{"__type__":"cc.SpriteFrame","content":{"name":"Common (12)","texture":"73No2pnf9Iz7LzhRncubTB","rect":[718,692,40,50],"offset":[-1,0],"originalSize":[42,50],"capInsets":[0,0,0,0]}},{"__type__":"cc.SpriteFrame","content":{"name":"Common (80)","texture":"73No2pnf9Iz7LzhRncubTB","rect":[867,434,78,70],"offset":[0,-3],"originalSize":[84,84],"capInsets":[0,0,0,0]}},{"__type__":"cc.SpriteFrame","content":{"name":"Common (75)","texture":"73No2pnf9Iz7LzhRncubTB","rect":[947,414,64,86],"offset":[0,5],"originalSize":[86,96],"capInsets":[0,0,0,0]}},{"__type__":"cc.SpriteFrame","content":{"name":"Common (141)","texture":"73No2pnf9Iz7LzhRncubTB","rect":[946,650,58,22],"offset":[0,0],"originalSize":[58,22],"capInsets":[5,5,5,5]}},{"__type__":"cc.SpriteFrame","content":{"name":"Common (59)","texture":"73No2pnf9Iz7LzhRncubTB","rect":[672,750,54,58],"offset":[0,-3],"originalSize":[70,76],"capInsets":[0,0,0,0]}},{"__type__":"cc.SpriteFrame","content":{"name":"Common (147)","texture":"73No2pnf9Iz7LzhRncubTB","rect":[380,753,42,52],"offset":[0,0],"originalSize":[42,52],"capInsets":[0,0,0,0]}},{"__type__":"cc.SpriteFrame","content":{"name":"Common (74)","texture":"73No2pnf9Iz7LzhRncubTB","rect":[2,2,442,64],"offset":[0,0],"originalSize":[442,64],"capInsets":[0,0,0,0]}},{"__type__":"cc.SpriteFrame","content":{"name":"Common (61)","texture":"73No2pnf9Iz7LzhRncubTB","rect":[890,600,54,58],"offset":[-1,0],"originalSize":[64,70],"capInsets":[0,0,0,0]}},{"__type__":"cc.SpriteFrame","content":{"name":"Common (40)","texture":"73No2pnf9Iz7LzhRncubTB","rect":[534,370,140,36],"offset":[0,0],"originalSize":[140,36],"capInsets":[0,0,0,0]}},{"__type__":"cc.SpriteFrame","content":{"name":"Common (69)","texture":"73No2pnf9Iz7LzhRncubTB","rect":[355,559,22,22],"offset":[0,0],"originalSize":[22,22],"capInsets":[0,0,0,0]}},{"__type__":"cc.SpriteFrame","content":{"name":"Common (112)","texture":"73No2pnf9Iz7LzhRncubTB","rect":[866,278,148,52],"offset":[0,0],"originalSize":[148,52],"capInsets":[0,0,0,0]}},{"__type__":"cc.SpriteFrame","content":{"name":"Common (58)","texture":"73No2pnf9Iz7LzhRncubTB","rect":[760,750,50,40],"offset":[0,0],"originalSize":[50,40],"capInsets":[0,0,0,0]}},{"__type__":"cc.SpriteFrame","content":{"name":"Common (24)","texture":"73No2pnf9Iz7LzhRncubTB","rect":[194,354,220,30],"offset":[0,0],"originalSize":[220,30],"capInsets":[0,0,0,0]}},{"__type__":"cc.SpriteFrame","content":{"name":"Common (36)","texture":"73No2pnf9Iz7LzhRncubTB","rect":[938,674,50,32],"offset":[0,0],"originalSize":[50,50],"capInsets":[0,0,0,0]}},{"__type__":"cc.SpriteFrame","content":{"name":"Common (133)","texture":"73No2pnf9Iz7LzhRncubTB","rect":[536,326,166,16],"offset":[0,0],"originalSize":[166,16],"capInsets":[0,0,0,0]}},{"__type__":"cc.SpriteFrame","content":{"name":"Common (140)","texture":"73No2pnf9Iz7LzhRncubTB","rect":[676,370,114,70],"offset":[0,0],"originalSize":[114,70],"capInsets":[0,0,0,0]}},{"__type__":"cc.SpriteFrame","content":{"name":"Common (21)","texture":"73No2pnf9Iz7LzhRncubTB","rect":[880,746,30,40],"offset":[0,0],"originalSize":[30,40],"capInsets":[6,6,6,6]}},{"__type__":"cc.SpriteFrame","content":{"name":"Common (119)","texture":"73No2pnf9Iz7LzhRncubTB","rect":[606,670,56,80],"offset":[1,0],"originalSize":[90,90],"capInsets":[0,0,0,0]}},{"__type__":"cc.SpriteFrame","content":{"name":"Common (111)","texture":"73No2pnf9Iz7LzhRncubTB","rect":[792,370,70,70],"offset":[0,0],"originalSize":[70,70],"capInsets":[0,0,0,0]}},{"__type__":"cc.SpriteFrame","content":{"name":"Common (51)","texture":"73No2pnf9Iz7LzhRncubTB","rect":[378,150,152,88],"offset":[-1,0],"originalSize":[164,88],"capInsets":[0,0,0,0]}},{"__type__":"cc.SpriteFrame","content":{"name":"Common (47)","texture":"73No2pnf9Iz7LzhRncubTB","rect":[944,564,70,26],"offset":[0,0],"originalSize":[70,26],"capInsets":[0,0,0,0]}},{"__type__":"cc.SpriteFrame","content":{"name":"Common (45)","texture":"73No2pnf9Iz7LzhRncubTB","rect":[355,583,20,20],"offset":[0,0],"originalSize":[20,20],"capInsets":[5,5,5,5]}},{"__type__":"cc.SpriteFrame","content":{"name":"Common (46)","texture":"73No2pnf9Iz7LzhRncubTB","rect":[760,680,70,26],"offset":[0,0],"originalSize":[70,26],"capInsets":[0,0,0,0]}},{"__type__":"cc.SpriteFrame","content":{"name":"Common (11)","texture":"73No2pnf9Iz7LzhRncubTB","rect":[252,605,126,92],"offset":[0,1],"originalSize":[140,140],"capInsets":[0,0,0,0]}},{"__type__":"cc.SpriteFrame","content":{"name":"Common (48)","texture":"73No2pnf9Iz7LzhRncubTB","rect":[878,198,140,40],"offset":[0,0],"originalSize":[140,40],"capInsets":[10,13,10,11]}},{"__type__":"cc.SpriteFrame","content":{"name":"Common (5)","texture":"73No2pnf9Iz7LzhRncubTB","rect":[844,788,40,32],"offset":[0,1],"originalSize":[40,40],"capInsets":[0,0,0,0]}},{"__type__":"cc.SpriteFrame","content":{"name":"Common (2)","texture":"73No2pnf9Iz7LzhRncubTB","rect":[946,592,56,56],"offset":[0,0],"originalSize":[56,56],"capInsets":[0,0,0,0]}},{"__type__":"cc.SpriteFrame","content":{"name":"Common (82)","texture":"73No2pnf9Iz7LzhRncubTB","rect":[412,816,60,72],"offset":[-1,-2],"originalSize":[84,84],"capInsets":[0,0,0,0]}},{"__type__":"cc.SpriteFrame","content":{"name":"Common (55)","texture":"73No2pnf9Iz7LzhRncubTB","rect":[194,170,182,100],"offset":[0,0],"originalSize":[182,100],"capInsets":[0,0,0,0]}},{"__type__":"cc.SpriteFrame","content":{"name":"Common (149)","texture":"73No2pnf9Iz7LzhRncubTB","rect":[716,574,40,74],"offset":[0,0],"originalSize":[40,74],"capInsets":[16,16,16,15]}},{"__type__":"cc.SpriteFrame","content":{"name":"Common (32)","texture":"73No2pnf9Iz7LzhRncubTB","rect":[776,792,34,34],"offset":[0,0],"originalSize":[34,34],"capInsets":[0,0,0,0]}},{"__type__":"cc.SpriteFrame","content":{"name":"Common (41)","texture":"73No2pnf9Iz7LzhRncubTB","rect":[878,240,140,36],"offset":[0,0],"originalSize":[140,36],"capInsets":[0,0,0,0]}},{"__type__":"cc.SpriteFrame","content":{"name":"Common (148)","texture":"73No2pnf9Iz7LzhRncubTB","rect":[600,548,52,120],"offset":[0,0],"originalSize":[52,120],"capInsets":[21,21,21,21]}},{"__type__":"cc.SpriteFrame","content":{"name":"Common (9)","texture":"73No2pnf9Iz7LzhRncubTB","rect":[904,2,114,114],"offset":[0,-4],"originalSize":[140,140],"capInsets":[0,0,0,0]}},{"__type__":"cc.SpriteFrame","content":{"name":"Common (78)","texture":"73No2pnf9Iz7LzhRncubTB","rect":[574,744,30,56],"offset":[0,0],"originalSize":[30,56],"capInsets":[0,0,0,0]}},{"__type__":"cc.SpriteFrame","content":{"name":"Common (54)","texture":"73No2pnf9Iz7LzhRncubTB","rect":[2,504,236,100],"offset":[0,0],"originalSize":[236,100],"capInsets":[0,0,0,0]}},{"__type__":"cc.SpriteFrame","content":{"name":"Common (87)","texture":"73No2pnf9Iz7LzhRncubTB","rect":[240,499,113,104],"offset":[0,0],"originalSize":[113,104],"capInsets":[0,0,0,0]}},{"__type__":"cc.SpriteFrame","content":{"name":"Common (122)","texture":"73No2pnf9Iz7LzhRncubTB","rect":[355,501,32,32],"offset":[0,0],"originalSize":[32,32],"capInsets":[0,0,0,0]}},{"__type__":"cc.SpriteFrame","content":{"name":"Common (106)","texture":"73No2pnf9Iz7LzhRncubTB","rect":[662,526,103,10],"offset":[0,0],"originalSize":[103,10],"capInsets":[3,3,10,3]}},{"__type__":"cc.SpriteFrame","content":{"name":"Common (49)","texture":"73No2pnf9Iz7LzhRncubTB","rect":[378,240,26,30],"offset":[0,0],"originalSize":[26,30],"capInsets":[0,0,0,0]}},{"__type__":"cc.SpriteFrame","content":{"name":"Common (103)","texture":"73No2pnf9Iz7LzhRncubTB","rect":[164,358,28,26],"offset":[0,0],"originalSize":[28,26],"capInsets":[6,6,6,6]}},{"__type__":"cc.SpriteFrame","content":{"name":"Common (28)","texture":"73No2pnf9Iz7LzhRncubTB","rect":[348,70,186,78],"offset":[0,0],"originalSize":[186,78],"capInsets":[0,0,0,0]}},{"__type__":"cc.SpriteFrame","content":{"name":"Common (159)","texture":"73No2pnf9Iz7LzhRncubTB","rect":[714,650,40,40],"offset":[0,0],"originalSize":[40,40],"capInsets":[0,0,0,0]}},{"__type__":"cc.SpriteFrame","content":{"name":"Common (56)","texture":"73No2pnf9Iz7LzhRncubTB","rect":[832,680,58,22],"offset":[0,0],"originalSize":[58,22],"capInsets":[4,4,4,4]}},{"__type__":"cc.SpriteFrame","content":{"name":"Common (50)","texture":"73No2pnf9Iz7LzhRncubTB","rect":[390,740,92,4],"offset":[0,0],"originalSize":[92,4],"capInsets":[0,0,0,0]}},{"__type__":"cc.SpriteFrame","content":{"name":"Common (92)","texture":"73No2pnf9Iz7LzhRncubTB","rect":[164,459,190,38],"offset":[0,0],"originalSize":[190,38],"capInsets":[0,0,0,0]}},{"__type__":"cc.SpriteFrame","content":{"name":"Common (33)","texture":"73No2pnf9Iz7LzhRncubTB","rect":[956,786,34,34],"offset":[0,0],"originalSize":[34,34],"capInsets":[0,0,0,0]}},{"__type__":"cc.SpriteAtlas","_name":"Common_2.plist","_spriteFrames":{"Common (1)":{"__uuid__":"4fme1gCXtGXb6yH68D2r3D"},"Common (10)":{"__uuid__":"5fFyZcrU9En4kTUErbYRWj"},"Common (100)":{"__uuid__":"fa5w7SwJJBg5iscn4bjkp8"},"Common (101)":{"__uuid__":"43RioXTEZBnaw13dP9sQiz"},"Common (102)":{"__uuid__":"5fyfBI2WRJcYXYNr6c+Yqo"},"Common (103)":{"__uuid__":"cbGVaeB15HV4e3jqjpj4OY"},"Common (104)":{"__uuid__":"58ZLIwXG9MT7XWPPy4RBYX"},"Common (105)":{"__uuid__":"34skscdRVJH7Mls39U9h3W"},"Common (106)":{"__uuid__":"c7wqTnRwpCNayNSXKRaHFv"},"Common (107)":{"__uuid__":"d5Sd0oi0JDL6+WONb+aJPK"},"Common (108)":{"__uuid__":"6fFgf299lLNrbLFr9xWjOf"},"Common (109)":{"__uuid__":"3buC2xhxlA5Yc2VwVMhswK"},"Common (11)":{"__uuid__":"b5492Ee89EoqQEA4zrl08Z"},"Common (110)":{"__uuid__":"7a3bu274ZE0ZeucKJ5aoFW"},"Common (111)":{"__uuid__":"aeBnT63FpFk4oEmtcBzaAp"},"Common (112)":{"__uuid__":"a1ecVUdhJMvrHNg8b22UI8"},"Common (113)":{"__uuid__":"07cM2KWAFAPbtiY+EVSEu0"},"Common (114)":{"__uuid__":"39wEVG+BlFVYnw3OzMIyTl"},"Common (115)":{"__uuid__":"1cPtx5cR5C/LOQ7t+6Jedl"},"Common (116)":{"__uuid__":"4f1oVn04FI0KSKV+sfbRQO"},"Common (117)":{"__uuid__":"e8lvhk3ERIcrVwPQZMiOVr"},"Common (118)":{"__uuid__":"78mrkmtEtM54sV9yQ6gmjS"},"Common (119)":{"__uuid__":"aaLtca5RNOhaRIQmzhSZSy"},"Common (12)":{"__uuid__":"8cZ5nTTZhAvY0MfCo4N0S7"},"Common (120)":{"__uuid__":"7esDwR5jVMjbbKpoOiBKpa"},"Common (121)":{"__uuid__":"e9UvQfLeRExY4gRDYIxgzF"},"Common (122)":{"__uuid__":"c63QRKe85M5ZnOR4QcZF1+"},"Common (123)":{"__uuid__":"4a9baZYvhOpoA3457XbtSi"},"Common (124)":{"__uuid__":"dcLe5+6QRHgLypYgBjajKX"},"Common (125)":{"__uuid__":"f5DopK1CNE2YxUTkooGChd"},"Common (126)":{"__uuid__":"688PBzgLROtom6h1+Wh3OF"},"Common (127)":{"__uuid__":"e6bneTYcVIWY1BBvzQiqZ/"},"Common (128)":{"__uuid__":"04/vhUNntI5JI6gSJNKrnM"},"Common (129)":{"__uuid__":"2ajvj9NYVCJpOAMy3zCGln"},"Common (13)":{"__uuid__":"e9bwAgEAJOGaRFdvthSsrh"},"Common (130)":{"__uuid__":"e9nx30z6FE07xr3Vga8wmw"},"Common (131)":{"__uuid__":"eaGXYZxi9OdpOKXOyHXEpx"},"Common (132)":{"__uuid__":"47oWrfbPhPJpp+wfPnouGj"},"Common (133)":{"__uuid__":"a60dCa0l9ErJ8DJbrrp+z2"},"Common (134)":{"__uuid__":"fdw5a+wchFrZYypBehCpYF"},"Common (135)":{"__uuid__":"33fpW1tjBJMaNqjcDWQET7"},"Common (136)":{"__uuid__":"87J3m8+XFMNbsJligdvH40"},"Common (137)":{"__uuid__":"1cPnmGympCg4pDmwQ0GtZq"},"Common (138)":{"__uuid__":"33v4/LiMFGiqxQwZ3LnY2d"},"Common (139)":{"__uuid__":"f89CoR5yhJ74GJVahfCazT"},"Common (14)":{"__uuid__":"64JeVW8lBLUJv7Sk4vAHkI"},"Common (140)":{"__uuid__":"a7S+npP+dO7KyXJfpzmzZh"},"Common (141)":{"__uuid__":"95oS6K609BuYzf8UApSMQU"},"Common (142)":{"__uuid__":"28NyLeLr9Gwr/C7wQdmYPC"},"Common (143)":{"__uuid__":"f6BToENC5OQKQWwum84gxR"},"Common (144)":{"__uuid__":"42Ly0kcnxFn7u+UbXOFVY0"},"Common (145)":{"__uuid__":"e77+ieHFxPsKIBd9VfnaFp"},"Common (146)":{"__uuid__":"0f8mj1v2pCToMZrlA/bcwa"},"Common (147)":{"__uuid__":"98K877kWBHRqLblNHZcif3"},"Common (148)":{"__uuid__":"c1ZCWULItMqKD/y1jVO52S"},"Common (149)":{"__uuid__":"bcaghIfkRO6LnqxPFlQtLn"},"Common (15)":{"__uuid__":"123zZ4kgBMmZecJGd1I5gi"},"Common (150)":{"__uuid__":"f4YUFqZjFP3p3FYgwYiLgA"},"Common (151)":{"__uuid__":"57PUNimkVKbKsPC06ddk28"},"Common (152)":{"__uuid__":"f10z8+a7FFGYfjUIN6PB+l"},"Common (153)":{"__uuid__":"4fhuRc25FIyqots+tSdKNb"},"Common (154)":{"__uuid__":"6f8Ut1OxlH64D3YEeGUDJl"},"Common (155)":{"__uuid__":"e9NL6xTJJFdIA1Q0ndP+Jk"},"Common (156)":{"__uuid__":"fcCt7x4DRNLLkwEan6G0Q5"},"Common (157)":{"__uuid__":"84YhZfuAhA7aApgmA86wIo"},"Common (158)":{"__uuid__":"7fsiZkayhG0r286jaOLAxQ"},"Common (159)":{"__uuid__":"cdYMc+GFNHxqfQUI42Be1p"},"Common (16)":{"__uuid__":"1cFbX+TZBAFqsHiqVcTQxS"},"Common (160)":{"__uuid__":"01r/DqNhZIC4NhBdiWNzsC"},"Common (161)":{"__uuid__":"e8FAku3IFGQ5D0JB8AEDet"},"Common (17)":{"__uuid__":"62H3AKhv9H2q5nvKeVUc66"},"Common (18)":{"__uuid__":"72qrtA7CBDa4jP6RqBQyJP"},"Common (19)":{"__uuid__":"24E/2f/3RMxazZQSmD5keO"},"Common (2)":{"__uuid__":"b8PVl8+ZpK2qwygG5Z68vm"},"Common (20)":{"__uuid__":"e9xLOsi19KUo6KGH4TcELS"},"Common (21)":{"__uuid__":"a8TRa+toNO9a7n5LFv21J8"},"Common (22)":{"__uuid__":"33hU0fDG9DBrA1QTdmtqop"},"Common (23)":{"__uuid__":"3aWpCSLgxPm5f1MQRSdygB"},"Common (24)":{"__uuid__":"a2IVcfP5VAnpYdj4kLjA4w"},"Common (25)":{"__uuid__":"fbtEmezeJD7KDNsVDvYqCi"},"Common (26)":{"__uuid__":"6ckwDsBRdN1pPNasylOKe2"},"Common (27)":{"__uuid__":"fbUuS9ggZNxIR9q1JEXaO6"},"Common (28)":{"__uuid__":"ccl1LqGTdKrpRK9tej3gsZ"},"Common (29)":{"__uuid__":"407YE7nF1OlIHIsXyMVMUK"},"Common (3)":{"__uuid__":"5dYYoVJfBJeKaOeHGkESj+"},"Common (30)":{"__uuid__":"8cPD1GtoNJYK8mfx9pQ6XK"},"Common (31)":{"__uuid__":"e7JDtyrk5GdbXRXsC8z+gU"},"Common (32)":{"__uuid__":"c0HY5v8cBPhLY0nmrbYzNE"},"Common (33)":{"__uuid__":"d0FB9VkTNIS6Y+jgrFP0hk"},"Common (34)":{"__uuid__":"71UJv5l15NUogtr0NqHKEg"},"Common (35)":{"__uuid__":"5a0N+O+4FFI69MXFkClo84"},"Common (36)":{"__uuid__":"a22IMSmPlApoHtuatF+Rwd"},"Common (37)":{"__uuid__":"fcEfFRvMJP64S5pkDUBj10"},"Common (38)":{"__uuid__":"71Mj4hrTBN1ZDjF7jEHMFP"},"Common (39)":{"__uuid__":"12nwpA2cxMUKUlZZryEXhc"},"Common (4)":{"__uuid__":"ddgSuvzyFMTrvOvO8FvBFZ"},"Common (40)":{"__uuid__":"a0q0I3ytRHtq1JduwzPf1w"},"Common (41)":{"__uuid__":"c1VGDxFx9PGr1eX9OyA2D8"},"Common (42)":{"__uuid__":"f9zxfzH7lJtJgur1RdA1Q3"},"Common (43)":{"__uuid__":"7ciiknHq1FarLCYi9m9xQ6"},"Common (44)":{"__uuid__":"e2EkE6NwRMPadH3G/3Hakh"},"Common (45)":{"__uuid__":"b2WeofPSlHO47raA3mmlXt"},"Common (46)":{"__uuid__":"b5tqX/XgtFda1wHkRr4n82"},"Common (47)":{"__uuid__":"b2JTJtLbBMXJSS7+wWH3LE"},"Common (48)":{"__uuid__":"b6SmkSCH5NUbTihBSzs0C3"},"Common (49)":{"__uuid__":"caSWu1trpPL57wgpqlmbZ2"},"Common (5)":{"__uuid__":"b688Q8zQBAdZUEbnv8hnOZ"},"Common (50)":{"__uuid__":"cfW6UcynlCSY5rW+gvuD73"},"Common (51)":{"__uuid__":"b14fK3EyBL9qeo0L+9chTT"},"Common (52)":{"__uuid__":"1aI3XXPGhH+r85vm64Y/6o"},"Common (53)":{"__uuid__":"5fYjnGQipNW62iSXpPMJNa"},"Common (54)":{"__uuid__":"c4mtLdCItJQp4rgfCGxk4g"},"Common (55)":{"__uuid__":"bbsB+VAXBDd6UcDy5Scryg"},"Common (56)":{"__uuid__":"cedLnlQ05FcbFMEoO0NtOs"},"Common (57)":{"__uuid__":"e5f7aD8TBFZ6nRJM5AKIOd"},"Common (58)":{"__uuid__":"a1s2DejKhGV6jmUu2Y7iyx"},"Common (59)":{"__uuid__":"97yVR5mvlBEoMGQxmSGBQm"},"Common (6)":{"__uuid__":"45Dhyx+vtHUr44VCIkMqWg"},"Common (60)":{"__uuid__":"61caI80lhKuaeCXNQJWW6X"},"Common (61)":{"__uuid__":"9e0x+yGc5Ct460uqZG432q"},"Common (62)":{"__uuid__":"07uBMrP4pEGK6QmvUSDwx5"},"Common (63)":{"__uuid__":"20GEiHekZBXZLWTNKqRgQq"},"Common (64)":{"__uuid__":"8audclczxD0I+qKVeEhcRB"},"Common (65)":{"__uuid__":"2av9wDIpJInoUMvuWDdohJ"},"Common (66)":{"__uuid__":"7c0e6gvw9M3ZlqXIh4PDOs"},"Common (67)":{"__uuid__":"ecxyFB/O5OfKJ6XRFEwv9/"},"Common (68)":{"__uuid__":"71Exq0zTZBKLoxkyuZWrA5"},"Common (69)":{"__uuid__":"a1bmpOlHBBWJ1s5Frwom77"},"Common (7)":{"__uuid__":"74MhgcwyFLCIKaClU4dAqS"},"Common (70)":{"__uuid__":"31QatVjGhNZZb5Kn2wFPE9"},"Common (71)":{"__uuid__":"76ycqI6AFCLYRjX6QtxOyl"},"Common (72)":{"__uuid__":"40baeZ7IlKIZSnXtzmgPkX"},"Common (73)":{"__uuid__":"3cIdm/QJFE2LGAG/r51tMm"},"Common (74)":{"__uuid__":"9eog0OietFOo8dFt0mBFnw"},"Common (75)":{"__uuid__":"92kBT6JqZMpbaXWmFBLpbg"},"Common (76)":{"__uuid__":"58aGbRBf1A/JMx3E3qDNoY"},"Common (77)":{"__uuid__":"86g74iI/5Kj44BqJwDwzqo"},"Common (78)":{"__uuid__":"c3DKQoEFtMwZMWJbI9/vk8"},"Common (79)":{"__uuid__":"34SYV18KtIYIYQOIQvMKEi"},"Common (8)":{"__uuid__":"52xcnPsVNE4LI8pb+1H+vB"},"Common (80)":{"__uuid__":"90GPp2vIpLeZqrCeDtZ6AC"},"Common (81)":{"__uuid__":"30LTk4QFRP9pj18Gm1AuGk"},"Common (82)":{"__uuid__":"bbGIvP+X9HqbAcY6JDbbrG"},"Common (83)":{"__uuid__":"82edtu7a1PFoZ4TjVj8ZgZ"},"Common (84)":{"__uuid__":"77wXtORlJF9plgaCYRC5JF"},"Common (85)":{"__uuid__":"45BN2gyWdGHJ+bAmjq3bNi"},"Common (86)":{"__uuid__":"0b9jwJYN5KT7E+JQojs22G"},"Common (87)":{"__uuid__":"c6roFn5w5E9asb4DMXyFaQ"},"Common (9)":{"__uuid__":"c15RjiSzdCELjwpixQfRgX"},"Common (92)":{"__uuid__":"cfytQQAxhD27l4qMXCzYz7"},"Common (93)":{"__uuid__":"e0Bg6fYIBPK7dlsVs65R2g"},"Common (94)":{"__uuid__":"26O3iepa5M0bUY/wUDt8Sb"},"Common (95)":{"__uuid__":"dcsycpRddL+I0uwXkRMo4w"},"Common (96)":{"__uuid__":"25g+r05ZhAipIfv7YKU1yr"},"Common (97)":{"__uuid__":"1b8pDagYlH45R7aP70ElED"},"Common (98)":{"__uuid__":"7fdHXjBXVAjaHqpca2O69y"},"Common (99)":{"__uuid__":"dd4Z8lxctBe4zdLE8T2C9R"}}},{"__type__":"cc.SpriteFrame","content":{"name":"Common (107)","texture":"73No2pnf9Iz7LzhRncubTB","rect":[490,660,10,10],"offset":[0,0],"originalSize":[10,10],"capInsets":[3,3,3,3]}},{"__type__":"cc.SpriteFrame","content":{"name":"Common (124)","texture":"73No2pnf9Iz7LzhRncubTB","rect":[886,788,36,36],"offset":[0,0],"originalSize":[36,36],"capInsets":[0,0,0,0]}},{"__type__":"cc.SpriteFrame","content":{"name":"Common (95)","texture":"73No2pnf9Iz7LzhRncubTB","rect":[2,734,226,71],"offset":[0,0],"originalSize":[226,71],"capInsets":[0,0,0,0]}},{"__type__":"cc.SpriteFrame","content":{"name":"Common (4)","texture":"73No2pnf9Iz7LzhRncubTB","rect":[844,822,36,30],"offset":[1,0],"originalSize":[40,40],"capInsets":[0,0,0,0]}},{"__type__":"cc.SpriteFrame","content":{"name":"Common (99)","texture":"73No2pnf9Iz7LzhRncubTB","rect":[662,538,84,34],"offset":[0,0],"originalSize":[84,34],"capInsets":[0,0,0,0]}},{"__type__":"cc.SpriteFrame","content":{"name":"Common (93)","texture":"73No2pnf9Iz7LzhRncubTB","rect":[744,838,30,30],"offset":[0,0],"originalSize":[30,30],"capInsets":[0,0,0,0]}},{"__type__":"cc.SpriteFrame","content":{"name":"Common (44)","texture":"73No2pnf9Iz7LzhRncubTB","rect":[760,870,20,20],"offset":[0,0],"originalSize":[20,20],"capInsets":[5,5,5,5]}},{"__type__":"cc.SpriteFrame","content":{"name":"Common (57)","texture":"73No2pnf9Iz7LzhRncubTB","rect":[844,854,30,30],"offset":[0,0],"originalSize":[30,30],"capInsets":[12,12,12,12]}},{"__type__":"cc.SpriteFrame","content":{"name":"Common (127)","texture":"73No2pnf9Iz7LzhRncubTB","rect":[714,870,22,22],"offset":[0,0],"originalSize":[22,22],"capInsets":[0,0,0,0]}},{"__type__":"cc.SpriteFrame","content":{"name":"Common (31)","texture":"73No2pnf9Iz7LzhRncubTB","rect":[854,40,34,28],"offset":[0,0],"originalSize":[34,34],"capInsets":[0,0,0,0]}},{"__type__":"cc.SpriteFrame","content":{"name":"Common (145)","texture":"73No2pnf9Iz7LzhRncubTB","rect":[724,198,152,70],"offset":[0,0],"originalSize":[152,70],"capInsets":[38,25,46,34]}},{"__type__":"cc.SpriteFrame","content":{"name":"Common (161)","texture":"73No2pnf9Iz7LzhRncubTB","rect":[824,552,58,66],"offset":[0,-2],"originalSize":[60,76],"capInsets":[0,0,0,0]}},{"__type__":"cc.SpriteFrame","content":{"name":"Common (117)","texture":"73No2pnf9Iz7LzhRncubTB","rect":[474,816,24,72],"offset":[0,0],"originalSize":[24,72],"capInsets":[10,11,10,11]}},{"__type__":"cc.SpriteFrame","content":{"name":"Common (155)","texture":"73No2pnf9Iz7LzhRncubTB","rect":[568,812,64,63],"offset":[0,0],"originalSize":[64,63],"capInsets":[0,0,0,0]}},{"__type__":"cc.SpriteFrame","content":{"name":"Common (121)","texture":"73No2pnf9Iz7LzhRncubTB","rect":[812,750,30,50],"offset":[0,0],"originalSize":[30,50],"capInsets":[12,14,12,12]}},{"__type__":"cc.SpriteFrame","content":{"name":"Common (13)","texture":"73No2pnf9Iz7LzhRncubTB","rect":[882,826,32,28],"offset":[0,0],"originalSize":[32,28],"capInsets":[0,0,0,0]}},{"__type__":"cc.SpriteFrame","content":{"name":"Common (130)","texture":"73No2pnf9Iz7LzhRncubTB","rect":[276,807,134,86],"offset":[0,0],"originalSize":[134,86],"capInsets":[0,0,0,0]}},{"__type__":"cc.SpriteFrame","content":{"name":"Common (20)","texture":"73No2pnf9Iz7LzhRncubTB","rect":[924,782,30,40],"offset":[0,0],"originalSize":[30,40],"capInsets":[6,6,6,6]}},{"__type__":"cc.SpriteFrame","content":{"name":"Common (131)","texture":"73No2pnf9Iz7LzhRncubTB","rect":[140,807,134,86],"offset":[0,0],"originalSize":[134,86],"capInsets":[28,26,28,28]}},{"__type__":"cc.SpriteFrame","content":{"name":"Common (67)","texture":"73No2pnf9Iz7LzhRncubTB","rect":[704,342,132,26],"offset":[0,0],"originalSize":[132,26],"capInsets":[0,0,0,0]}},{"__type__":"cc.SpriteFrame","content":{"name":"Common (152)","texture":"73No2pnf9Iz7LzhRncubTB","rect":[2,606,248,68],"offset":[0,0],"originalSize":[248,68],"capInsets":[0,0,0,0]}},{"__type__":"cc.SpriteFrame","content":{"name":"Common (150)","texture":"73No2pnf9Iz7LzhRncubTB","rect":[536,200,180,60],"offset":[0,0],"originalSize":[180,60],"capInsets":[11,11,11,11]}},{"__type__":"cc.SpriteFrame","content":{"name":"Common (125)","texture":"73No2pnf9Iz7LzhRncubTB","rect":[892,704,44,36],"offset":[0,-1],"originalSize":[46,40],"capInsets":[0,0,0,0]}},{"__type__":"cc.SpriteFrame","content":{"name":"Common (143)","texture":"73No2pnf9Iz7LzhRncubTB","rect":[527,408,132,62],"offset":[0,0],"originalSize":[132,62],"capInsets":[0,0,0,0]}},{"__type__":"cc.SpriteFrame","content":{"name":"Common (139)","texture":"73No2pnf9Iz7LzhRncubTB","rect":[782,870,18,18],"offset":[0,0],"originalSize":[18,18],"capInsets":[0,0,0,0]}},{"__type__":"cc.SpriteFrame","content":{"name":"Common (42)","texture":"73No2pnf9Iz7LzhRncubTB","rect":[661,442,124,20],"offset":[0,0],"originalSize":[124,20],"capInsets":[0,0,0,0]}},{"__type__":"cc.SpriteFrame","content":{"name":"Common (100)","texture":"73No2pnf9Iz7LzhRncubTB","rect":[760,708,54,40],"offset":[0,0],"originalSize":[54,40],"capInsets":[0,0,0,0]}},{"__type__":"cc.SpriteFrame","content":{"name":"Common (27)","texture":"73No2pnf9Iz7LzhRncubTB","rect":[724,70,178,48],"offset":[0,0],"originalSize":[178,48],"capInsets":[0,0,0,0]}},{"__type__":"cc.SpriteFrame","content":{"name":"Common (25)","texture":"73No2pnf9Iz7LzhRncubTB","rect":[2,676,246,56],"offset":[0,0],"originalSize":[246,56],"capInsets":[0,0,0,0]}},{"__type__":"cc.SpriteFrame","content":{"name":"Common (156)","texture":"73No2pnf9Iz7LzhRncubTB","rect":[758,616,64,62],"offset":[0,0],"originalSize":[64,62],"capInsets":[0,0,0,0]}},{"__type__":"cc.SpriteFrame","content":{"name":"Common (37)","texture":"73No2pnf9Iz7LzhRncubTB","rect":[980,710,38,38],"offset":[-4,-1],"originalSize":[46,40],"capInsets":[4,4,4,4]}},{"__type__":"cc.SpriteFrame","content":{"name":"Common (134)","texture":"73No2pnf9Iz7LzhRncubTB","rect":[824,620,64,58],"offset":[0,0],"originalSize":[64,58],"capInsets":[0,0,0,0]}}]